MANIFEST.in
README.rst
requirements.txt
setup.py
Simple_AES_Cipher.egg-info/PKG-INFO
Simple_AES_Cipher.egg-info/SOURCES.txt
Simple_AES_Cipher.egg-info/dependency_links.txt
Simple_AES_Cipher.egg-info/requires.txt
Simple_AES_Cipher.egg-info/top_level.txt
simple_aes_cipher/__init__.py
simple_aes_cipher/cipher.py
simple_aes_cipher/secret_key.py
simple_aes_cipher/version.py
tests/__init__.py
tests/test_aes_cipher.py