Metadata-Version: 1.1
Name: Simple-AES-Cipher
Version: 1.0.7
Summary: Pycrypto based Simple And Easy Cipher on AES
Home-page: https://github.com/teitei-tk/Simple-AES-Cipher
Author: teitei-tk
Author-email: teitei.tk@gmail.com
License: MIT
Download-URL: https://github.com/teitei-tk/Simple-AES-Cipher/archive/master.tar.gz
Keywords: cipher,aes
Platform: UNKNOWN
Classifier: Development Status :: 5 - Production/Stable
Classifier: License :: OSI Approved :: MIT License
Classifier: Programming Language :: Python :: 2.7
Classifier: Programming Language :: Python :: 3
Classifier: Topic :: Software Development
Classifier: Topic :: Software Development :: Libraries
